datasette_litestream/__init__.py
datasette_litestream/templates/litestream.html
datasette_litestream-0.2a0.dist-info/licenses/LICENSE
datasette_litestream-0.2a0.dist-info/METADATA
datasette_litestream-0.2a0.dist-info/WHEEL
datasette_litestream-0.2a0.dist-info/entry_points.txt
datasette_litestream-0.2a0.dist-info/top_level.txt
datasette_litestream-0.2a0.dist-info/RECORD
