Metadata-Version: 2.4
Name: datasette-litestream
Version: 0.2a0
Author: Alex Garcia
License-Expression: Apache-2.0
Project-URL: Homepage, https://github.com/datasette/datasette-litestream
Project-URL: Changelog, https://github.com/datasette/datasette-litestream/releases
Project-URL: Issues, https://github.com/datasette/datasette-litestream/issues
Project-URL: CI, https://github.com/datasette/datasette-litestream/actions
Requires-Python: >=3.10
License-File: LICENSE
Requires-Dist: datasette>=1.0a20
Requires-Dist: prometheus-client
Dynamic: license-file
